LICENSE
MANIFEST.in
README.rst
REQUIREMENTS
distribute_setup.py
setup.py
hotwatch/__init__.py
hotwatch/cli.py
hotwatch/query.py
hotwatch.egg-info/PKG-INFO
hotwatch.egg-info/SOURCES.txt
hotwatch.egg-info/dependency_links.txt
hotwatch.egg-info/entry_points.txt
hotwatch.egg-info/requires.txt
hotwatch.egg-info/top_level.txt