Metadata-Version: 1.0
Name: hotwatch
Version: 0.1.2
Summary: HotWatch is a command line utility for monitoring the status of HotQueue queue instances.
Home-page: http://github.com/richardhenry/hotwatch
Author: Richard Henry
Author-email: richardhenry@me.com
License: MIT
Platform: UNKNOWN
Classifier: Programming Language :: Python
Classifier: Development Status :: 4 - Beta
Classifier: Intended Audience :: Developers
Classifier: License :: OSI Approved :: MIT License
Classifier: Operating System :: OS Independent
Classifier: Topic :: Software Development :: Libraries :: Python Modules
